loggingtestcase/__init__.py
loggingtestcase/capturelogs.py
loggingtestcase/loggingtestcase.py
logging_test_case-1.4.1.dist-info/LICENSE
logging_test_case-1.4.1.dist-info/METADATA
logging_test_case-1.4.1.dist-info/WHEEL
logging_test_case-1.4.1.dist-info/top_level.txt
logging_test_case-1.4.1.dist-info/RECORD
