Metadata-Version: 2.1
Name: logging-test-case
Version: 1.4.1
Summary: Provides class LoggingTestCase to help test log files.
Home-page: https://github.com/chadrosenquist/logging-test-case
Author: Chad Rosenquist
Author-email: chadrosenquist@gmail.com
License: MIT
Keywords: unit testing log files logging regression logging-test-case loggingtestcase
Platform: UNKNOWN
Requires-Python: >=3.4
